src/weight_stationary_pe.sv

`default_nettype none
`timescale 1ns/1ns

module weight_stationary_pe #(
  parameter DATA_WIDTH=8 // Bit width of weights and activations
)
(
  input wire clk,
  input wire reset,
  input wire load_weight,       // load the weight into the PE if this signal is high
  input wire valid,             // signal to indicate that new data is available

  input wire [DATA_WIDTH-1:0] input_in,       // input from the left adjacent PE or weight memory
  input wire [DATA_WIDTH-1:0] weight,     // weight stored in the PE
  input wire [DATA_WIDTH-1:0] psum_in,     // accumulated value from the PE above

  output reg [DATA_WIDTH-1:0] input_out,    // input to the right adjacent PE
  output reg [DATA_WIDTH-1:0] psum_out   // output value feeding into the PE below
);
    
  reg [DATA_WIDTH-1:0] weight_reg; // register used to store the weight when load_weight is high

  always @(posedge clk or posedge reset) begin
    if (reset) begin 
      // setting everything to 0 when the reset signal is high
      input_out <= 0;
      psum_out <= 0;
      weight_reg <= 0;

    end else begin

      if (load_weight) begin
        weight_reg <= weight; // load the weight into the PE
      end 

      // if (valid) begin
        psum_out <= psum_in + (input_in * weight_reg); // compute the new accumulated value
        input_out <= input_in; // pass the input to the right adjacent PE
      // end 

    end
  end
endmodule





// `default_nettype none
// `timescale 1ns/1ns

// module processing_element (
//   input wire clk,
//   input wire reset,
//   input wire load_weight,       // Signal to load weight
//   input wire valid,             // Valid signal indicating new data is available

//   input wire [7:0] a_in,       // Input A from left neighbor
//   input wire [7:0] weight,     // Weight input
//   input wire [7:0] acc_in,     // Accumulated value from the PE above

//   output reg [7:0] a_out,    // Output A to right neighbor
//   output reg [7:0] acc_out   // Accumulated value to the PE below
// );

//   reg [7:0] weight_reg; // Register to hold the stationary weight

//   always @(posedge clk or posedge reset) begin
//     if (reset) begin
      
//       a_out <= 8'b0;
//       acc_out <= 8'b0;
//       weight_reg <= 8'b0;

//     end else begin

//       if (load_weight) begin
//         weight_reg <= weight;
//       end 

//       if (valid) begin // means compute!
//         acc_out <= acc_in + (a_in * weight_reg);
//         a_out <= a_in;
//       end

//     end
//   end
// endmodule

src/systolic_array.sv
module systolic_array #(parameter DATA_WIDTH=8) 
(
    input wire clk,
    input wire reset,
    input wire load_weights,
    input wire start,

    input wire [DATA_WIDTH-1:0] w00,
    input wire [DATA_WIDTH-1:0] w01,
    input wire [DATA_WIDTH-1:0] w10,
    input wire [DATA_WIDTH-1:0] w11,

    input wire [DATA_WIDTH-1:0] x0,
    input wire [DATA_WIDTH-1:0] x1,

    output wire [DATA_WIDTH-1:0] y0,
    output wire [DATA_WIDTH-1:0] y1,

    output reg done
);

   
    wire [DATA_WIDTH-1:0] input_inter0;
    wire [DATA_WIDTH-1:0] input_inter1;

    wire [DATA_WIDTH-1:0] psum_inter0;
    wire [DATA_WIDTH-1:0] psum_inter1;

     wire [DATA_WIDTH-1:0] zero_wire;
    assign zero_wire = 8'b0;

    weight_stationary_pe PE00 (
        .clk(clk),
        .reset(reset),
        .load_weight(load_weights),
        .valid(start),
        .input_in(x0),
        .weight(w00),
        .psum_in(zero_wire),
        .input_out(input_inter0),
        .psum_out(psum_inter0)
    );

    weight_stationary_pe PE01 (
        .clk(clk),
        .reset(reset),
        .load_weight(load_weights),
        .valid(start),
        .input_in(input_inter0),
        .weight(w01),
        .psum_in(zero_wire),
        .input_out(),
        .psum_out(psum_inter1)
    );

    weight_stationary_pe PE10 (
        .clk(clk),
        .reset(reset),
        .load_weight(load_weights),
        .valid(start),
        .input_in(x1),
        .weight(w10),
        .psum_in(psum_inter0),
        .input_out(input_inter1),
        .psum_out(y0)
    );

    weight_stationary_pe PE11 (
        .clk(clk),
        .reset(reset),
        .load_weight(load_weights),
        .valid(start),
        .input_in(input_inter1),
        .weight(w11),
        .psum_in(psum_inter1),
        .input_out(),
        .psum_out(y1)
    );

endmodule

sys_array.vcd
$date
	Tue Mar  4 11:29:57 2025
$end
$version
	Icarus Verilog
$end
$timescale
	1ns
$end
$scope module systolic_array $end
$var wire 1 ! clk $end
$var wire 1 " load_weights $end
$var wire 1 # reset $end
$var wire 1 $ start $end
$var wire 8 % w00 [7:0] $end
$var wire 8 & w01 [7:0] $end
$var wire 8 ' w10 [7:0] $end
$var wire 8 ( w11 [7:0] $end
$var wire 8 ) x0 [7:0] $end
$var wire 8 * x1 [7:0] $end
$var wire 8 + zero_wire [7:0] $end
$var wire 8 , y1 [7:0] $end
$var wire 8 - y0 [7:0] $end
$var wire 8 . psum_inter1 [7:0] $end
$var wire 8 / psum_inter0 [7:0] $end
$var wire 8 0 input_inter1 [7:0] $end
$var wire 8 1 input_inter0 [7:0] $end
$var parameter 32 2 DATA_WIDTH $end
$var reg 1 3 done $end
$scope module PE00 $end
$var wire 1 ! clk $end
$var wire 8 4 input_in [7:0] $end
$var wire 1 " load_weight $end
$var wire 8 5 psum_in [7:0] $end
$var wire 1 # reset $end
$var wire 1 $ valid $end
$var wire 8 6 weight [7:0] $end
$var parameter 32 7 DATA_WIDTH $end
$var reg 8 8 input_out [7:0] $end
$var reg 8 9 psum_out [7:0] $end
$var reg 8 : weight_reg [7:0] $end
$upscope $end
$scope module PE01 $end
$var wire 1 ! clk $end
$var wire 8 ; input_in [7:0] $end
$var wire 1 " load_weight $end
$var wire 8 < psum_in [7:0] $end
$var wire 1 # reset $end
$var wire 1 $ valid $end
$var wire 8 = weight [7:0] $end
$var parameter 32 > DATA_WIDTH $end
$var reg 8 ? input_out [7:0] $end
$var reg 8 @ psum_out [7:0] $end
$var reg 8 A weight_reg [7:0] $end
$upscope $end
$scope module PE10 $end
$var wire 1 ! clk $end
$var wire 8 B input_in [7:0] $end
$var wire 1 " load_weight $end
$var wire 8 C psum_in [7:0] $end
$var wire 1 # reset $end
$var wire 1 $ valid $end
$var wire 8 D weight [7:0] $end
$var parameter 32 E DATA_WIDTH $end
$var reg 8 F input_out [7:0] $end
$var reg 8 G psum_out [7:0] $end
$var reg 8 H weight_reg [7:0] $end
$upscope $end
$scope module PE11 $end
$var wire 1 ! clk $end
$var wire 8 I input_in [7:0] $end
$var wire 1 " load_weight $end
$var wire 8 J psum_in [7:0] $end
$var wire 1 # reset $end
$var wire 1 $ valid $end
$var wire 8 K weight [7:0] $end
$var parameter 32 L DATA_WIDTH $end
$var reg 8 M input_out [7:0] $end
$var reg 8 N psum_out [7:0] $end
$var reg 8 O weight_reg [7:0] $end
$upscope $end
$upscope $end
$enddefinitions $end
$comment Show the parameter values. $end
$dumpall
b1000 L
b1000 E
b1000 >
b1000 7
b1000 2
$end
#0
$dumpvars
b0 O
b0 N
b0 M
b0 K
b0 J
b0 I
b0 H
b0 G
b0 F
b0 D
b0 C
b0 B
b0 A
b0 @
b0 ?
b0 =
b0 <
b0 ;
b0 :
b0 9
b0 8
b0 6
b0 5
b0 4
03
b0 1
b0 0
b0 /
b0 .
b0 -
b0 ,
b0 +
b0 *
b0 )
b0 (
b0 '
b0 &
b0 %
0$
1#
0"
1!
$end
#5
0!
#10
1!
0#
#15
0!
#20
b1 :
b10 A
b11 H
b100 O
1!
b100 (
b100 K
b11 '
b11 D
b10 &
b10 =
b1 %
b1 6
1"
#25
0!
#30
1!
1$
#35
0!
#40
b101 1
b101 8
b101 ;
b101 /
b101 9
b101 C
1!
b101 )
b101 4
#45
0!
#50
b111 0
b111 F
b111 I
b11010 -
b11010 G
b101 ?
b1010 .
b1010 @
b1010 J
b110 1
b110 8
b110 ;
b110 /
b110 9
b110 C
1!
b111 *
b111 B
b110 )
b110 4
#55
0!
#60
b0 1
b0 8
b0 ;
b0 /
b0 9
b0 C
b110 ?
b1100 .
b1100 @
b1100 J
b1000 0
b1000 F
b1000 I
b11110 -
b11110 G
b111 M
b100110 ,
b100110 N
1!
b1000 *
b1000 B
b0 )
b0 4
#65
0!
#70
b1000 M
b101100 ,
b101100 N
b0 0
b0 F
b0 I
b0 -
b0 G
b0 ?
b0 .
b0 @
b0 J
1!
b0 *
b0 B
#75
0!
#80
b0 M
b0 ,
b0 N
1!
13
